hollarek/__init__.py
hollarek/cloud.py
hollarek/cloud/__init__.py
hollarek/cloud/entities/EC2Template.py
hollarek/cloud/entities/__init__.py
hollarek/cloud/entities/enums.py
hollarek/cloud/manager/__init__.py
hollarek/cloud/manager/manager.py
hollarek/cloud/services/__init__.py
hollarek/cloud/services/database.py
hollarek/cloud/services/ec2.py
hollarek/cloud/services/iam.py
hollarek/cloud/services/lambda_aws.py
hollarek/configs/__init__.py
hollarek/configs/abstr.py
hollarek/configs/configs.py
hollarek/crypt/__init__.py
hollarek/crypt/encrypt/__init__.py
hollarek/crypt/encrypt/aes.py
hollarek/crypt/encrypt/algo.py
hollarek/crypt/encrypt/rsa.py
hollarek/crypt/hash/__init__.py
hollarek/crypt/hash/salt.py
hollarek/crypt/hash/sha.py
hollarek/dev/__init__.py
hollarek/dev/dtyping/__init__.py
hollarek/dev/dtyping/get_core.py
hollarek/dev/hardware/__init__.py
hollarek/dev/hardware/drives.py
hollarek/dev/hardware/ram.py
hollarek/dev/hardware/usage.py
hollarek/dev/log/__init__.py
hollarek/dev/log/formatter.py
hollarek/dev/log/log_settings.py
hollarek/dev/log/loggable.py
hollarek/dev/log/logger.py
hollarek/dev/test/__init__.py
hollarek/dev/test/test_runners.py
hollarek/dev/test/unit.py
hollarek/devtools/__init__.py
hollarek/devtools/hardware/__init__.py
hollarek/devtools/hardware/drives.py
hollarek/devtools/hardware/ram.py
hollarek/devtools/hardware/usage.py
hollarek/devtools/inspection/__init__.py
hollarek/devtools/inspection/dtypes.py
hollarek/devtools/inspection/module_inspection.py
hollarek/devtools/inspection/optional.py
hollarek/devtools/spoof/__init__.py
hollarek/devtools/spoof/filespoofer.py
hollarek/devtools/spoof/spoof.bin
hollarek/devtools/spoof/spoof.csv
hollarek/devtools/spoof/spoof.jpg
hollarek/devtools/spoof/spoof.pdf
hollarek/devtools/spoof/spoof.png
hollarek/devtools/spoof/spoof.txt
hollarek/devtools/spoof/spoofs.py
hollarek/devtools/spoof/__pycache__/__init__.cpython-310.pyc
hollarek/devtools/spoof/__pycache__/filespoofer.cpython-310.pyc
hollarek-0.9.1.dist-info/LICENSE.txt
hollarek-0.9.1.dist-info/METADATA
hollarek-0.9.1.dist-info/WHEEL
hollarek-0.9.1.dist-info/top_level.txt
hollarek-0.9.1.dist-info/RECORD
